Workbook

Sheet Configuracion
A1: OPTISAVE — PANEL DE CONFIGURACIÓN COMERCIAL
A2: Modifica solo las celdas resaltadas en amarillo. El resto del archivo se recalcula solo.
A4: 1. PRECIOS DE LICENCIA
A5: Precio licencia Doctor (mensual) | B5: 250
A6: Precio licencia Desktop (anual) | B6: 4500
A7: Comisión fija Desktop (por licencia) | B7: 1000
A8: IVA (México) | B8: 0.16
A10: 2. COMISIONES DOCTOR (por tramo de licencias nuevas / mes, sobre 1er pago)
A11: Tramo (licencias nuevas/mes) | B11: Desde | C11: Hasta | D11: % Comisión (1er pago)
A12: 1–24 nuevas licencias | B12: 1 | C12: 24 | D12: 0.3
A13: 25–49 nuevas licencias | B13: 25 | C13: 49 | D13: 0.4
A14: 50+ nuevas licencias | B14: 50 | C14: 9999 | D14: 0.5
A16: 3. BONO TRIMESTRAL DE PERMANENCIA (por doctores activos al cierre de trimestre)
A17: Tramo (doctores activos) | B17: Desde | C17: Hasta | D17: Bono ($ MXN)
A18: 1–24 doctores activos | B18: 1 | C18: 24 | D18: 1500
A19: 25–49 doctores activos | B19: 25 | C19: 49 | D19: 4000
A20: 50–99 doctores activos | B20: 50 | C20: 99 | D20: 9000
A21: 100+ doctores activos | B21: 100 | C21: 99999 | D21: 20000
A23: Nota: los tramos son por 'monto', no acumulables (no marginal). El % o bono aplica a todo el volumen del periodo según el tramo alcanzado.

Sheet Dashboard MRR
A1: OPTISAVE — DASHBOARD MRR / ARR Y DECISIÓN COMERCIAL
A2: Este panel se alimenta automáticamente de las hojas de Comisiones y Bono. No requiere captura.
A4: INGRESOS (SIN IVA)
A5: MRR — Licencias Doctor (mes capturado) | B5: ='Comisiones Doctores'!$G$30 -> 12000
A6: Ingreso Licencias Desktop (anual, mes capturado) | B6: ='Comisiones Desktop'!$E$30 -> 13500
A7: Ingreso Desktop normalizado a mensual (÷12) | B7: =B6/12 -> 1125
A8: MRR TOTAL (Doctor + Desktop/12) | B8: =B5+B7 -> 13125
A9: ARR ESTIMADO (MRR x 12) | B9: =B8*12 -> 157500
A11: IVA (16%)
A12: IVA sobre licencias Doctor | B12: ='Comisiones Doctores'!$I$30 -> 1920
A13: IVA sobre licencias Desktop | B13: ='Comisiones Desktop'!$G$30 -> 2160
A14: IVA TOTAL a trasladar (informativo, no es ingreso) | B14: =B13+B12 -> 4080
A16: COSTO COMERCIAL (COMISIONES + BONO)
A17: Comisión pagada — Licencias Doctor | B17: ='Comisiones Doctores'!$H$30 -> 4350
A18: Comisión pagada — Licencias Desktop | B18: ='Comisiones Desktop'!$F$30 -> 3000
A19: Bono trimestral de permanencia | B19: ='Bono Trimestral'!$E$22 -> 4000
A20: TOTAL COSTO COMERCIAL | B20: =B17+B18+B19 -> 11350
A22: RENTABILIDAD Y DECISIÓN
A23: Ingreso total del periodo (sin IVA) | B23: ='Comisiones Doctores'!$G$30+'Comisiones Desktop'!$E$30 -> 25500
A24: Utilidad neta (Ingreso − Costo comercial) | B24: =B23-B20 -> 14150
A25: % Costo comercial sobre ingreso | B25: =IFERROR(B20/B23,0) -> 0.44509804
A26: % Margen neto sobre ingreso | B26: =IFERROR(B24/B23,0) -> 0.55490196
A28: SEMÁFORO DE DECISIÓN (referencia)
A29: Margen neto ≥ 55% → Esquema saludable | 40–55% → Vigilar | < 40% → Revisar comisiones/precio
A31: Fuente de cifras: hojas 'Comisiones Doctores', 'Comisiones Desktop' y 'Bono Trimestral'. Ajusta precios y % en 'Configuracion'.

Sheet Comisiones Doctores
A1: COMISIONES — LICENCIAS DOCTOR (MENSUAL, POR EJECUTIVO)
A2: Llena las columnas amarillas: Mes, Ejecutivo y # Licencias nuevas vendidas ese mes. El resto se calcula solo.
A4: Mes | B4: Ejecutivo Comercial | C4: # Licencias nuevas | D4: Precio licencia | E4: % Comisión aplicable | F4: Tramo alcanzado | G4: Ingreso 1er pago (sin IVA) | H4: Comisión ($) | I4: IVA de licencias (16%)
A5: Ene-2026 | B5: Ana Torres | C5: 18 | D5: =Configuracion!$B$5 -> 250 | E5: =IF(C5="","",INDEX(Configuracion!$D$12:$D$14,MATCH(C5,Configuracion!$B$12:$B$14,1))) -> 0.3 | F5: =IF(C5="","",INDEX(Configuracion!$A$12:$A$14,MATCH(C5,Configuracion!$B$12:$B$14,1))) -> 1–24 nuevas licencias | G5: =IF(C5="","",C5*D5) -> 4500 | H5: =IF(C5="","",G5*E5) -> 1350 | I5: =IF(C5="","",G5*Configuracion!$B$8) -> 720
A6: Ene-2026 | B6: Luis Medina | C6: 30 | D6: =Configuracion!$B$5 -> 250 | E6: =IF(C6="","",INDEX(Configuracion!$D$12:$D$14,MATCH(C6,Configuracion!$B$12:$B$14,1))) -> 0.4 | F6: =IF(C6="","",INDEX(Configuracion!$A$12:$A$14,MATCH(C6,Configuracion!$B$12:$B$14,1))) -> 25–49 nuevas licencias | G6: =IF(C6="","",C6*D6) -> 7500 | H6: =IF(C6="","",G6*E6) -> 3000 | I6: =IF(C6="","",G6*Configuracion!$B$8) -> 1200
D7: =Configuracion!$B$5 -> 250 | E7: =IF(C7="","",INDEX(Configuracion!$D$12:$D$14,MATCH(C7,Configuracion!$B$12:$B$14,1))) | F7: =IF(C7="","",INDEX(Configuracion!$A$12:$A$14,MATCH(C7,Configuracion!$B$12:$B$14,1))) | G7: =IF(C7="","",C7*D7) | H7: =IF(C7="","",G7*E7) | I7: =IF(C7="","",G7*Configuracion!$B$8)
D8: =Configuracion!$B$5 -> 250 | E8: =IF(C8="","",INDEX(Configuracion!$D$12:$D$14,MATCH(C8,Configuracion!$B$12:$B$14,1))) | F8: =IF(C8="","",INDEX(Configuracion!$A$12:$A$14,MATCH(C8,Configuracion!$B$12:$B$14,1))) | G8: =IF(C8="","",C8*D8) | H8: =IF(C8="","",G8*E8) | I8: =IF(C8="","",G8*Configuracion!$B$8)
D9: =Configuracion!$B$5 -> 250 | E9: =IF(C9="","",INDEX(Configuracion!$D$12:$D$14,MATCH(C9,Configuracion!$B$12:$B$14,1))) | F9: =IF(C9="","",INDEX(Configuracion!$A$12:$A$14,MATCH(C9,Configuracion!$B$12:$B$14,1))) | G9: =IF(C9="","",C9*D9) | H9: =IF(C9="","",G9*E9) | I9: =IF(C9="","",G9*Configuracion!$B$8)
D10: =Configuracion!$B$5 -> 250 | E10: =IF(C10="","",INDEX(Configuracion!$D$12:$D$14,MATCH(C10,Configuracion!$B$12:$B$14,1))) | F10: =IF(C10="","",INDEX(Configuracion!$A$12:$A$14,MATCH(C10,Configuracion!$B$12:$B$14,1))) | G10: =IF(C10="","",C10*D10) | H10: =IF(C10="","",G10*E10) | I10: =IF(C10="","",G10*Configuracion!$B$8)
D11: =Configuracion!$B$5 -> 250 | E11: =IF(C11="","",INDEX(Configuracion!$D$12:$D$14,MATCH(C11,Configuracion!$B$12:$B$14,1))) | F11: =IF(C11="","",INDEX(Configuracion!$A$12:$A$14,MATCH(C11,Configuracion!$B$12:$B$14,1))) | G11: =IF(C11="","",C11*D11) | H11: =IF(C11="","",G11*E11) | I11: =IF(C11="","",G11*Configuracion!$B$8)
D12: =Configuracion!$B$5 -> 250 | E12: =IF(C12="","",INDEX(Configuracion!$D$12:$D$14,MATCH(C12,Configuracion!$B$12:$B$14,1))) | F12: =IF(C12="","",INDEX(Configuracion!$A$12:$A$14,MATCH(C12,Configuracion!$B$12:$B$14,1))) | G12: =IF(C12="","",C12*D12) | H12: =IF(C12="","",G12*E12) | I12: =IF(C12="","",G12*Configuracion!$B$8)
D13: =Configuracion!$B$5 -> 250 | E13: =IF(C13="","",INDEX(Configuracion!$D$12:$D$14,MATCH(C13,Configuracion!$B$12:$B$14,1))) | F13: =IF(C13="","",INDEX(Configuracion!$A$12:$A$14,MATCH(C13,Configuracion!$B$12:$B$14,1))) | G13: =IF(C13="","",C13*D13) | H13: =IF(C13="","",G13*E13) | I13: =IF(C13="","",G13*Configuracion!$B$8)
D14: =Configuracion!$B$5 -> 250 | E14: =IF(C14="","",INDEX(Configuracion!$D$12:$D$14,MATCH(C14,Configuracion!$B$12:$B$14,1))) | F14: =IF(C14="","",INDEX(Configuracion!$A$12:$A$14,MATCH(C14,Configuracion!$B$12:$B$14,1))) | G14: =IF(C14="","",C14*D14) | H14: =IF(C14="","",G14*E14) | I14: =IF(C14="","",G14*Configuracion!$B$8)
D15: =Configuracion!$B$5 -> 250 | E15: =IF(C15="","",INDEX(Configuracion!$D$12:$D$14,MATCH(C15,Configuracion!$B$12:$B$14,1))) | F15: =IF(C15="","",INDEX(Configuracion!$A$12:$A$14,MATCH(C15,Configuracion!$B$12:$B$14,1))) | G15: =IF(C15="","",C15*D15) | H15: =IF(C15="","",G15*E15) | I15: =IF(C15="","",G15*Configuracion!$B$8)
D16: =Configuracion!$B$5 -> 250 | E16: =IF(C16="","",INDEX(Configuracion!$D$12:$D$14,MATCH(C16,Configuracion!$B$12:$B$14,1))) | F16: =IF(C16="","",INDEX(Configuracion!$A$12:$A$14,MATCH(C16,Configuracion!$B$12:$B$14,1))) | G16: =IF(C16="","",C16*D16) | H16: =IF(C16="","",G16*E16) | I16: =IF(C16="","",G16*Configuracion!$B$8)
D17: =Configuracion!$B$5 -> 250 | E17: =IF(C17="","",INDEX(Configuracion!$D$12:$D$14,MATCH(C17,Configuracion!$B$12:$B$14,1))) | F17: =IF(C17="","",INDEX(Configuracion!$A$12:$A$14,MATCH(C17,Configuracion!$B$12:$B$14,1))) | G17: =IF(C17="","",C17*D17) | H17: =IF(C17="","",G17*E17) | I17: =IF(C17="","",G17*Configuracion!$B$8)
D18: =Configuracion!$B$5 -> 250 | E18: =IF(C18="","",INDEX(Configuracion!$D$12:$D$14,MATCH(C18,Configuracion!$B$12:$B$14,1))) | F18: =IF(C18="","",INDEX(Configuracion!$A$12:$A$14,MATCH(C18,Configuracion!$B$12:$B$14,1))) | G18: =IF(C18="","",C18*D18) | H18: =IF(C18="","",G18*E18) | I18: =IF(C18="","",G18*Configuracion!$B$8)
... D28: =Configuracion!$B$5 -> 250 | E28: =IF(C28="","",INDEX(Configuracion!$D$12:$D$14,MATCH(C28,Configuracion!$B$12:$B$14,1))) | F28: =IF(C28="","",INDEX(Configuracion!$A$12:$A$14,MATCH(C28,Configuracion!$B$12:$B$14,1))) | G28: =IF(C28="","",C28*D28) | H28: =IF(C28="","",G28*E28) | I28: =IF(C28="","",G28*Configuracion!$B$8)
B30: TOTALES | C30: =SUM(C5:C28) -> 48 | G30: =SUM(G5:G28) -> 12000 | H30: =SUM(H5:H28) -> 4350 | I30: =SUM(I5:I28) -> 1920

Sheet Comisiones Desktop
A1: COMISIONES — LICENCIA DESKTOP (ANUAL)
A2: Llena Mes, Ejecutivo y # Licencias Desktop vendidas. Comisión fija por licencia (Configuración).
A4: Mes | B4: Ejecutivo Comercial | C4: # Licencias Desktop | D4: Precio licencia (anual) | E4: Ingreso (sin IVA) | F4: Comisión ($ fija/licencia) | G4: IVA (16%)
A5: Ene-2026 | B5: Ana Torres | C5: 3 | D5: =Configuracion!$B$6 -> 4500 | E5: =IF(C5="","",C5*D5) -> 13500 | F5: =IF(C5="","",C5*Configuracion!$B$7) -> 3000 | G5: =IF(C5="","",E5*Configuracion!$B$8) -> 2160
D6: =Configuracion!$B$6 -> 4500 | E6: =IF(C6="","",C6*D6) | F6: =IF(C6="","",C6*Configuracion!$B$7) | G6: =IF(C6="","",E6*Configuracion!$B$8)
D7: =Configuracion!$B$6 -> 4500 | E7: =IF(C7="","",C7*D7) | F7: =IF(C7="","",C7*Configuracion!$B$7) | G7: =IF(C7="","",E7*Configuracion!$B$8)
D8: =Configuracion!$B$6 -> 4500 | E8: =IF(C8="","",C8*D8) | F8: =IF(C8="","",C8*Configuracion!$B$7) | G8: =IF(C8="","",E8*Configuracion!$B$8)
D9: =Configuracion!$B$6 -> 4500 | E9: =IF(C9="","",C9*D9) | F9: =IF(C9="","",C9*Configuracion!$B$7) | G9: =IF(C9="","",E9*Configuracion!$B$8)
D10: =Configuracion!$B$6 -> 4500 | E10: =IF(C10="","",C10*D10) | F10: =IF(C10="","",C10*Configuracion!$B$7) | G10: =IF(C10="","",E10*Configuracion!$B$8)
D11: =Configuracion!$B$6 -> 4500 | E11: =IF(C11="","",C11*D11) | F11: =IF(C11="","",C11*Configuracion!$B$7) | G11: =IF(C11="","",E11*Configuracion!$B$8)
D12: =Configuracion!$B$6 -> 4500 | E12: =IF(C12="","",C12*D12) | F12: =IF(C12="","",C12*Configuracion!$B$7) | G12: =IF(C12="","",E12*Configuracion!$B$8)
D13: =Configuracion!$B$6 -> 4500 | E13: =IF(C13="","",C13*D13) | F13: =IF(C13="","",C13*Configuracion!$B$7) | G13: =IF(C13="","",E13*Configuracion!$B$8)
D14: =Configuracion!$B$6 -> 4500 | E14: =IF(C14="","",C14*D14) | F14: =IF(C14="","",C14*Configuracion!$B$7) | G14: =IF(C14="","",E14*Configuracion!$B$8)
D15: =Configuracion!$B$6 -> 4500 | E15: =IF(C15="","",C15*D15) | F15: =IF(C15="","",C15*Configuracion!$B$7) | G15: =IF(C15="","",E15*Configuracion!$B$8)
D16: =Configuracion!$B$6 -> 4500 | E16: =IF(C16="","",C16*D16) | F16: =IF(C16="","",C16*Configuracion!$B$7) | G16: =IF(C16="","",E16*Configuracion!$B$8)
D17: =Configuracion!$B$6 -> 4500 | E17: =IF(C17="","",C17*D17) | F17: =IF(C17="","",C17*Configuracion!$B$7) | G17: =IF(C17="","",E17*Configuracion!$B$8)
... D28: =Configuracion!$B$6 -> 4500 | E28: =IF(C28="","",C28*D28) | F28: =IF(C28="","",C28*Configuracion!$B$7) | G28: =IF(C28="","",E28*Configuracion!$B$8)
B30: TOTALES | C30: =SUM(C5:C28) -> 3 | E30: =SUM(E5:E28) -> 13500 | F30: =SUM(F5:F28) -> 3000 | G30: =SUM(G5:G28) -> 2160

Sheet Bono Trimestral
A1: BONO TRIMESTRAL DE PERMANENCIA
A2: Llena Trimestre, Ejecutivo y # Doctores activos (con licencia vigente) al cierre del trimestre.
A4: Trimestre | B4: Ejecutivo Comercial | C4: # Doctores activos | D4: Tramo alcanzado | E4: Bono ($ MXN)
A5: Q1-2026 | B5: Ana Torres | C5: 32 | D5: =IF(C5="","",INDEX(Configuracion!$A$18:$A$21,MATCH(C5,Configuracion!$B$18:$B$21,1))) -> 25–49 doctores activos | E5: =IF(C5="","",INDEX(Configuracion!$D$18:$D$21,MATCH(C5,Configuracion!$B$18:$B$21,1))) -> 4000
D6: =IF(C6="","",INDEX(Configuracion!$A$18:$A$21,MATCH(C6,Configuracion!$B$18:$B$21,1))) | E6: =IF(C6="","",INDEX(Configuracion!$D$18:$D$21,MATCH(C6,Configuracion!$B$18:$B$21,1)))
D7: =IF(C7="","",INDEX(Configuracion!$A$18:$A$21,MATCH(C7,Configuracion!$B$18:$B$21,1))) | E7: =IF(C7="","",INDEX(Configuracion!$D$18:$D$21,MATCH(C7,Configuracion!$B$18:$B$21,1)))
D8: =IF(C8="","",INDEX(Configuracion!$A$18:$A$21,MATCH(C8,Configuracion!$B$18:$B$21,1))) | E8: =IF(C8="","",INDEX(Configuracion!$D$18:$D$21,MATCH(C8,Configuracion!$B$18:$B$21,1)))
D9: =IF(C9="","",INDEX(Configuracion!$A$18:$A$21,MATCH(C9,Configuracion!$B$18:$B$21,1))) | E9: =IF(C9="","",INDEX(Configuracion!$D$18:$D$21,MATCH(C9,Configuracion!$B$18:$B$21,1)))
D10: =IF(C10="","",INDEX(Configuracion!$A$18:$A$21,MATCH(C10,Configuracion!$B$18:$B$21,1))) | E10: =IF(C10="","",INDEX(Configuracion!$D$18:$D$21,MATCH(C10,Configuracion!$B$18:$B$21,1)))
D11: =IF(C11="","",INDEX(Configuracion!$A$18:$A$21,MATCH(C11,Configuracion!$B$18:$B$21,1))) | E11: =IF(C11="","",INDEX(Configuracion!$D$18:$D$21,MATCH(C11,Configuracion!$B$18:$B$21,1)))
D12: =IF(C12="","",INDEX(Configuracion!$A$18:$A$21,MATCH(C12,Configuracion!$B$18:$B$21,1))) | E12: =IF(C12="","",INDEX(Configuracion!$D$18:$D$21,MATCH(C12,Configuracion!$B$18:$B$21,1)))
D13: =IF(C13="","",INDEX(Configuracion!$A$18:$A$21,MATCH(C13,Configuracion!$B$18:$B$21,1))) | E13: =IF(C13="","",INDEX(Configuracion!$D$18:$D$21,MATCH(C13,Configuracion!$B$18:$B$21,1)))
D14: =IF(C14="","",INDEX(Configuracion!$A$18:$A$21,MATCH(C14,Configuracion!$B$18:$B$21,1))) | E14: =IF(C14="","",INDEX(Configuracion!$D$18:$D$21,MATCH(C14,Configuracion!$B$18:$B$21,1)))
D15: =IF(C15="","",INDEX(Configuracion!$A$18:$A$21,MATCH(C15,Configuracion!$B$18:$B$21,1))) | E15: =IF(C15="","",INDEX(Configuracion!$D$18:$D$21,MATCH(C15,Configuracion!$B$18:$B$21,1)))
D16: =IF(C16="","",INDEX(Configuracion!$A$18:$A$21,MATCH(C16,Configuracion!$B$18:$B$21,1))) | E16: =IF(C16="","",INDEX(Configuracion!$D$18:$D$21,MATCH(C16,Configuracion!$B$18:$B$21,1)))
D17: =IF(C17="","",INDEX(Configuracion!$A$18:$A$21,MATCH(C17,Configuracion!$B$18:$B$21,1))) | E17: =IF(C17="","",INDEX(Configuracion!$D$18:$D$21,MATCH(C17,Configuracion!$B$18:$B$21,1)))
... D20: =IF(C20="","",INDEX(Configuracion!$A$18:$A$21,MATCH(C20,Configuracion!$B$18:$B$21,1))) | E20: =IF(C20="","",INDEX(Configuracion!$D$18:$D$21,MATCH(C20,Configuracion!$B$18:$B$21,1)))
B22: TOTAL BONOS | E22: =SUM(E5:E20) -> 4000
